simpype/__init__.py
simpype/build.py
simpype/message.py
simpype/pipe.py
simpype/pipeline.py
simpype/queue.py
simpype/random.py
simpype/resource.py
simpype/simulation.py
simpype/model/__init__.py
simpype/model/generator.py
simpype/model/pipe.py
simpype/model/queue.py
simpype/model/resource.py
simpype-1.0.0rc10.dist-info/METADATA
simpype-1.0.0rc10.dist-info/WHEEL
simpype-1.0.0rc10.dist-info/top_level.txt
simpype-1.0.0rc10.dist-info/RECORD
