Metadata-Version: 2.1
Name: simpype
Version: 1.0.0rc10
Summary: SimPype is a simulation framework based on Simpy that relies on the concepts of resource and pipe.
Home-page: https://github.com/Mallets/SimPype/
Author: Luca Cominardi
Author-email: luca.cominardi@gmail.com
License: GPLv3+ License
Keywords: simulation queue pipe simpy
Platform: UNKNOWN
Classifier: Development Status :: 4 - Beta
Classifier: Environment :: Console
Classifier: Intended Audience :: Developers
Classifier: Intended Audience :: Education
Classifier: Intended Audience :: Science/Research
Classifier: Topic :: Scientific/Engineering
Classifier: License :: OSI Approved :: GNU General Public License v3 or later (GPLv3+)
Classifier: Programming Language :: Python :: 3 :: Only
Classifier: Programming Language :: Python :: 3.3
Classifier: Programming Language :: Python :: 3.4
Classifier: Programming Language :: Python :: 3.5
Classifier: Programming Language :: Python :: 3.6
Requires-Python: >=3.3
Requires-Dist: simpy (>=3.0.10)
